README.rst
setup.py
moyasar/__init__.py
moyasar/helpers.py
moyasar/invoice.py
moyasar/payment.py
moyasar/resource.py
moyasar.egg-info/PKG-INFO
moyasar.egg-info/SOURCES.txt
moyasar.egg-info/dependency_links.txt
moyasar.egg-info/requires.txt
moyasar.egg-info/top_level.txt
moyasar/actions/__init__.py
moyasar/actions/cancel.py
moyasar/actions/capture.py
moyasar/actions/create.py
moyasar/actions/fetch.py
moyasar/actions/list.py
moyasar/actions/refund.py
moyasar/actions/update.py
moyasar/actions/void.py
tests/__init__.py
tests/moyasar_test.py
tests/server_stubs.py
tests/moyasar/__init__.py
tests/moyasar/invoice_test.py
tests/moyasar/payment_test.py