Metadata-Version: 2.1
Name: moyasar
Version: 0.6.5
Summary: Moyasar Python language wrapper
Home-page: https://github.com/moyasar/moyasar-python
Author: Moyasar
Author-email: developers@moyasar.com
License: UNKNOWN
Download-URL: https://github.com/moyasar/moyasar-python/archive/v0.6.1.tar.gz
Platform: UNKNOWN
Classifier: Programming Language :: Python :: 3
Classifier: License :: OSI Approved :: MIT License
Classifier: Operating System :: OS Independent
